verge/__init__.py
verge/cli.py
verge/core.py
verge/tests/__init__.py
verge/tests/test_cli.py
verge/tests/test_core.py
verge-0.1.0.data/scripts/verge
verge-0.1.0.dist-info/DESCRIPTION.rst
verge-0.1.0.dist-info/METADATA
verge-0.1.0.dist-info/pydist.json
verge-0.1.0.dist-info/RECORD
verge-0.1.0.dist-info/top_level.txt
verge-0.1.0.dist-info/WHEEL
